{
 "banner": {
  "title": "⚠️ Регресс регистрации 09–16.07 — сломался один шаг",
  "html": "Обвалился <b>продукт → показ рег-попапа</b>: с ~<b>85%</b> до ~<b>55%</b>. Вход в продукт и форма не пострадали — попап стал показываться трети юзеров реже. <b>≈7 700</b> недобранных регистраций. Началось <b>09.07</b> (не совпадает с релизами 14 и 17.07), восстановилось 17.07."
 },
 "events": [
  {
   "d": "2026-07-09",
   "color": "amber",
   "label": "начало регресса реги"
  },
  {
   "d": "2026-07-14",
   "color": "gray",
   "label": "безлимитные одноразки"
  },
  {
   "d": "2026-07-17",
   "color": "teal",
   "label": "3 оффера (last-chance/welcome/sticky)"
  }
 ],
 "bands": [
  {
   "from": "2026-07-09",
   "to": "2026-07-16",
   "label": "провал регистрации"
  }
 ]
}